<?xml version="1.0" encoding="UTF-8" ?>

<filterSection formatVersion="3.2" name="M330_20140828_TEQ_v6" date="01-Sep-2014 17:20:30">
	<filter channelMask="0" fs="8000">
		<fir> 19952, -564, -4644, 1268, -44, 502, -128, 92, -68, 56, -44, 38, -30, 14 </fir>
	</filter>
	<filter channelMask="0" fs="11025">
		<fir> 17862, 3516, -3676, -2996, 1082, 176, 106, 358, -60, 32, -20, 14, -10, 8, -6, 14 </fir>
	</filter>
	<filter channelMask="0" fs="12000">
		<fir> 17492, 3820, -2482, -3736, 142, 832, -178, 364, 162, -42, 24, -16, 12, -8, 8, -6, 14 </fir>
	</filter>
	<filter channelMask="0" fs="16000">
		<fir> 32712, 8440, 392, -4560, -6368, -608, 1128, 1108, -500, 436, 576, 32, -24, 24, -20, 20, -16, 16, -16, 15 </fir>
	</filter>
	<filter channelMask="0" fs="22050">
		<fir> 28900, 10312, 2084, 156, -2472, -5324, -3276, -444, 640, 1092, 492, -264, -60, 476, 460, -4, 4, -4, 4, -4, 4, -4, 0, 15 </fir>
	</filter>
	<filter channelMask="0" fs="24000">
		<fir> 28120, 10236, 2816, 320, -1096, -4244, -4416, -1724, 36, 752, 976, 384, -256, -80, 360, 512, 92, -24, 12, -8, 4, -4, 4, -4, 15 </fir>
	</filter>
	<filter channelMask="0" fs="32000">
		<fir> 26060, 9000, 4848, 1308, 252, -348, -1972, -3532, -3332, -1864, -488, 180, 564, 736, 592, 128, -176, -160, 132, 308, 404, 152, -32, 16, -12, 8, -4, 4, -4, 15 </fir>
	</filter>
	<filter channelMask="0" fs="44100">
		<fir> 26004, 4468, 7576, 1108, 2412, -484, 496, -472, -1144, -2120, -2684, -2424, -1692, -864, -240, 88, 324, 460, 552, 460, 272, 16, -124, -152, -24, 100, 240, 252, 284, 92, -24, 12, 15 </fir>
	</filter>
	<filter channelMask="0" fs="48000">
		<fir> 26444, 2736, 8244, 1196, 2388, 344, -100, 308, -764, -1220, -2116, -2472, -2200, -1612, -880, -332, 12, 220, 368, 476, 492, 388, 196, 0, -124, -132, -48, 76, 184, 240, 248, 216, 15 </fir>
	</filter>
</filterSection>